brifc.cp313-win_amd64.pyd
brif/__init__.py
brif/brif.py
brif-1.4.7.dist-info/METADATA
brif-1.4.7.dist-info/WHEEL
brif-1.4.7.dist-info/top_level.txt
brif-1.4.7.dist-info/RECORD
