Metadata-Version: 2.4
Name: brif
Version: 1.4.7
Summary: Build decision trees and random forests for classification and regression.
Author: Yanchao Liu
Author-email: yanchaoliu@wayne.edu
License-Expression: GPL-3.0-only
Project-URL: Homepage, https://pypi.org/project/brif/
Project-URL: Source, https://github.com/profyliu/brif-python
Keywords: random forest,classification,regression,prediction
Classifier: Topic :: Scientific/Engineering :: Information Analysis
Classifier: Programming Language :: Python :: 3
Classifier: Programming Language :: Python :: 3.9
Classifier: Programming Language :: Python :: 3.10
Classifier: Programming Language :: Python :: 3.11
Classifier: Programming Language :: Python :: 3.12
Classifier: Programming Language :: C
Classifier: Programming Language :: Python :: Implementation :: CPython
Classifier: Operating System :: OS Independent
Requires-Python: >=3.9
Requires-Dist: numpy
Requires-Dist: pandas
